[
  { "name": "race_code_uma_kol", "type": "STRING", "description": "KOL仕様馬毎レースID 年月日6桁+KOL仕様開催場所コード2桁+開催回次2桁+開催日次2桁+レース番号2桁+馬番2桁" },
  { "name": "keibajo_code", "type": "STRING", "description": "KOL仕様 競馬場コード" },
  { "name": "kaisai_nen", "type": "STRING", "description": "開催年" },
  { "name": "kaisai_kaiji", "type": "STRING", "description": "開催回次" },
  { "name": "kaisai_nichiji", "type": "STRING", "description": "開催日次" },
  { "name": "race_num", "type": "STRING", "description": "レース番号" },
  { "name": "kaisai_nengappi", "type": "STRING", "description": "年月日" },
  { "name": "yobi_code", "type": "STRING", "description": "曜日コード" },
  { "name": "wakuban", "type": "STRING", "description": "枠番" },
  { "name": "umaban", "type": "STRING", "description": "馬番" },
  { "name": "ketto_toroku_bango", "type": "STRING", "description": "血統登録番号(馬コード)" },
  { "name": "bamei", "type": "STRING", "description": "馬名" },
  { "name": "umakigo_code", "type": "STRING", "description": "馬記号コード" },
  { "name": "seibetsu_code", "type": "STRING", "description": "性別コード" },
  { "name": "barei", "type": "STRING", "description": "馬齢" },
  { "name": "banushimei", "type": "STRING", "description": "馬主名" },
  { "name": "banushimei_ryakusho", "type": "STRING", "description": "馬主名略称" },
  { "name": "yobi_field_1", "type": "STRING", "description": "予備フィールド" },
  { "name": "blinker_shiyo_kubun", "type": "STRING", "description": "ブリンカー使用区分" },
  { "name": "futan_juryo", "type": "STRING", "description": "負担重量" },
  { "name": "kishu_code", "type": "STRING", "description": "騎手コード" },
  { "name": "kishumei", "type": "STRING", "description": "騎手名" },
  { "name": "kishumei_ryakusho", "type": "STRING", "description": "騎手名略称" },
  { "name": "kishu_tozai_shozoku_code", "type": "STRING", "description": "騎手東西所属コード" },
  { "name": "kishu_shozokubasho_code", "type": "STRING", "description": "騎手所属場所コード" },
  { "name": "kishu_shozoku_chokyoshi_code", "type": "STRING", "description": "騎手所属調教師コード" },
  { "name": "kishu_minarai_code", "type": "STRING", "description": "騎手見習コード" },
  { "name": "kishu_norikawari_kubun", "type": "STRING", "description": "騎手乗替区分" },
  { "name": "chokyoshi_code", "type": "STRING", "description": "調教師コード" },
  { "name": "chokyoshimei", "type": "STRING", "description": "調教師名" },
  { "name": "chokyoshimei_ryakusho", "type": "STRING", "description": "調教師名略称" },
  { "name": "chokyoshi_shozokubasho_code", "type": "STRING", "description": "調教師所属場所コード" },
  { "name": "chokyoshi_tracen_kubun", "type": "STRING", "description": "調教師トレセン区分" },
  { "name": "yoso_shirushi1", "type": "STRING", "description": "出馬表の予想印" },
  { "name": "yoso_shirushi2", "type": "STRING", "description": "予想(本紙)" },
  { "name": "chokyo1_flag", "type": "STRING", "description": "調教1 調教フラグ" },
  { "name": "chokyo1_kijosha", "type": "STRING", "description": "調教1 調教騎乗者" },
  { "name": "chokyo1_nengappi", "type": "STRING", "description": "調教1 調教年月日" },
  { "name": "chokyo1_basho", "type": "STRING", "description": "調教1 調教場所" },
  { "name": "chokyo1_course", "type": "STRING", "description": "調教1 調教コース" },
  { "name": "chokyo1_babajotai", "type": "STRING", "description": "調教1 調教馬場状態" },
  { "name": "chokyo1_8f", "type": "STRING", "description": "調教1 調教8F" },
  { "name": "chokyo1_7f", "type": "STRING", "description": "調教1 調教7F" },
  { "name": "chokyo1_6f", "type": "STRING", "description": "調教1 調教6F" },
  { "name": "chokyo1_5f", "type": "STRING", "description": "調教1 調教5F" },
  { "name": "chokyo1_4f", "type": "STRING", "description": "調教1 調教4F" },
  { "name": "chokyo1_3f", "type": "STRING", "description": "調教1 調教3F" },
  { "name": "chokyo1_1f", "type": "STRING", "description": "調教1 調教1F" },
  { "name": "chokyo1_ichidori", "type": "STRING", "description": "調教1 調教位置取り" },
  { "name": "chokyo1_ashiiro", "type": "STRING", "description": "調教1 調教脚色" },
  { "name": "chokyo1_yajirushi", "type": "STRING", "description": "調教1 調教矢印" },
  { "name": "chokyo1_reigai", "type": "STRING", "description": "調教1 調教例外" },
  { "name": "chokyo2_flag", "type": "STRING", "description": "調教2 調教フラグ" },
  { "name": "chokyo2_kijosha", "type": "STRING", "description": "調教2 調教騎乗者" },
  { "name": "chokyo2_nengappi", "type": "STRING", "description": "調教2 調教年月日" },
  { "name": "chokyo2_basho", "type": "STRING", "description": "調教2 調教場所" },
  { "name": "chokyo2_course", "type": "STRING", "description": "調教2 調教コース" },
  { "name": "chokyo2_babajotai", "type": "STRING", "description": "調教2 調教馬場状態" },
  { "name": "chokyo2_8f", "type": "STRING", "description": "調教2 調教8F" },
  { "name": "chokyo2_7f", "type": "STRING", "description": "調教2 調教7F" },
  { "name": "chokyo2_6f", "type": "STRING", "description": "調教2 調教6F" },
  { "name": "chokyo2_5f", "type": "STRING", "description": "調教2 調教5F" },
  { "name": "chokyo2_4f", "type": "STRING", "description": "調教2 調教4F" },
  { "name": "chokyo2_3f", "type": "STRING", "description": "調教2 調教3F" },
  { "name": "chokyo2_1f", "type": "STRING", "description": "調教2 調教1F" },
  { "name": "chokyo2_ichidori", "type": "STRING", "description": "調教2 調教位置取り" },
  { "name": "chokyo2_ashiiro", "type": "STRING", "description": "調教2 調教脚色" },
  { "name": "chokyo2_yajirushi", "type": "STRING", "description": "調教2 調教矢印" },
  { "name": "chokyo2_reigai", "type": "STRING", "description": "調教2 調教例外" },
  { "name": "chokyo3_flag", "type": "STRING", "description": "調教3 調教フラグ" },
  { "name": "chokyo3_kijosha", "type": "STRING", "description": "調教3 調教騎乗者" },
  { "name": "chokyo3_nengappi", "type": "STRING", "description": "調教3 調教年月日" },
  { "name": "chokyo3_basho", "type": "STRING", "description": "調教3 調教場所" },
  { "name": "chokyo3_course", "type": "STRING", "description": "調教3 調教コース" },
  { "name": "chokyo3_babajotai", "type": "STRING", "description": "調教3 調教馬場状態" },
  { "name": "chokyo3_8f", "type": "STRING", "description": "調教3 調教8F" },
  { "name": "chokyo3_7f", "type": "STRING", "description": "調教3 調教7F" },
  { "name": "chokyo3_6f", "type": "STRING", "description": "調教3 調教6F" },
  { "name": "chokyo3_5f", "type": "STRING", "description": "調教3 調教5F" },
  { "name": "chokyo3_4f", "type": "STRING", "description": "調教3 調教4F" },
  { "name": "chokyo3_3f", "type": "STRING", "description": "調教3 調教3F" },
  { "name": "chokyo3_1f", "type": "STRING", "description": "調教3 調教1F" },
  { "name": "chokyo3_ichidori", "type": "STRING", "description": "調教3 調教位置取り" },
  { "name": "chokyo3_ashiiro", "type": "STRING", "description": "調教3 調教脚色" },
  { "name": "chokyo3_yajirushi", "type": "STRING", "description": "調教3 調教矢印" },
  { "name": "chokyo3_reigai", "type": "STRING", "description": "調教3 調教例外" },
  { "name": "chokyo_awase_flg", "type": "STRING", "description": "調教併せフラグ" },
  { "name": "chokyo_awase", "type": "STRING", "description": "調教併せ" },
  { "name": "chokyo_tanpyo", "type": "STRING", "description": "調教短評" },
  { "name": "chokyo_honsu_course", "type": "STRING", "description": "調教本数 コース" },
  { "name": "chokyo_honsu_hanro", "type": "STRING", "description": "調教本数 坂路" },
  { "name": "chokyo_honsu_pool", "type": "STRING", "description": "調教本数 プール" },
  { "name": "data_sakusei_ymd", "type": "STRING", "description": "データ作成日" },
  { "name": "seinen", "type": "STRING", "description": "生年" },
  { "name": "rating", "type": "STRING", "description": "レイティング" },
  { "name": "speed_shisu5", "type": "STRING", "description": "スピード指数5" },
  { "name": "speed_shisu4", "type": "STRING", "description": "スピード指数4" },
  { "name": "speed_shisu3", "type": "STRING", "description": "スピード指数3" },
  { "name": "speed_shisu2", "type": "STRING", "description": "スピード指数2" },
  { "name": "speed_shisu1", "type": "STRING", "description": "スピード指数1" },
  { "name": "rotation8", "type": "STRING", "description": "ローテーション8" },
  { "name": "rotation7", "type": "STRING", "description": "ローテーション7" },
  { "name": "rotation6", "type": "STRING", "description": "ローテーション6" },
  { "name": "rotation5", "type": "STRING", "description": "ローテーション5" },
  { "name": "rotation4", "type": "STRING", "description": "ローテーション4" },
  { "name": "rotation3", "type": "STRING", "description": "ローテーション3" },
  { "name": "rotation2", "type": "STRING", "description": "ローテーション2" },
  { "name": "rotation1", "type": "STRING", "description": "ローテーション1" },
  { "name": "kyuyo_riyu", "type": "STRING", "description": "休養理由" },
  { "name": "bashobetsu_1chaku", "type": "STRING", "description": "場所別 1着" },
  { "name": "bashobetsu_2chaku", "type": "STRING", "description": "場所別 2着" },
  { "name": "bashobetsu_3chaku", "type": "STRING", "description": "場所別 3着" },
  { "name": "bashobetsu_chakugai", "type": "STRING", "description": "場所別 着外" },
  { "name": "yobi_field_2", "type": "STRING", "description": "予備フィールド" },
  { "name": "created", "type": "TIMESTAMP", "description": "データ作成日時" },
  { "name": "modified", "type": "TIMESTAMP", "description": "データ更新日時" }
]